{"data":{"allMarkdownRemark":{"edges":[{"node":{"frontmatter":{"title":"Dictionary App","date":"5 days ago","slug":"/dictionary-application","tags":["HTML","CSS","SCSS","React","Gatsby"],"posttype":"project","subtitle":"Dictionary Search and Vocabulary-Building Application","category":"Educative Game","primaryTech":"React","github":"https://github.com/wandrew8/dictionaryApp","website":"https://wandrew8.github.io/dictionaryApp/#/"}}},{"node":{"frontmatter":{"title":"Gatsby Portfolio","date":"4 months ago","slug":"/gatsby-application","tags":["HTML","CSS","SCSS","React","Gatsby"],"posttype":"project","subtitle":"Location-Based, FoodCommerce Application","category":"Social Media","primaryTech":"React","github":"https://github.com/wandrew8/dictionaryApp","website":"https://wandrew8.github.io/dictionaryApp/#/"}}},{"node":{"frontmatter":{"title":"Olaf","date":"5 days ago","slug":"/olaf-application","tags":["HTML","CSS","SCSS","React","Gatsby"],"posttype":"project","subtitle":"Location-Based, FoodCommerce Application","category":"E-Commerce","primaryTech":"JavaScript","github":"https://github.com/wandrew8/dictionaryApp","website":"https://wandrew8.github.io/dictionaryApp/#/"}}},{"node":{"frontmatter":{"title":"Hangman","date":"5 days ago","slug":"/hangman-application","tags":["HTML","CSS","SCSS","React","Gatsby"],"posttype":"project","subtitle":"Location-Based, FoodCommerce Application","category":"E-Commerce","primaryTech":"Gatsby","github":"https://github.com/wandrew8/dictionaryApp","website":"https://wandrew8.github.io/dictionaryApp/#/"}}},{"node":{"frontmatter":{"title":"Our First Post","date":"5 days ago","slug":"/first-post","tags":["HTML","CSS","SCSS","React","Gatsby","Third party API"],"posttype":"post","subtitle":null,"category":"UI Design","primaryTech":null,"github":null,"website":null}}},{"node":{"frontmatter":{"title":"Our Second Post","date":"4 days ago","slug":"/second-post","tags":["HTML","CSS","SCSS","React","Gatsby"],"posttype":"post","subtitle":null,"category":"Design","primaryTech":null,"github":null,"website":null}}}]}}}